md2pdf.py
md2pdf_mcp-0.1.4.dist-info/METADATA
md2pdf_mcp-0.1.4.dist-info/WHEEL
md2pdf_mcp-0.1.4.dist-info/entry_points.txt
md2pdf_mcp-0.1.4.dist-info/RECORD
