Metadata-Version: 2.4
Name: md2pdf-mcp
Version: 0.1.4
Summary: MCP Server for Markdown to PDF conversion
Project-URL: Homepage, https://github.com/chunliu/md2pdf
Project-URL: Repository, https://github.com/chunliu/md2pdf
Project-URL: Issues, https://github.com/chunliu/md2pdf/issues
Author-email: Chun Liu <chunliu@outlook.com>
License: MIT
Keywords: conversion,markdown,mcp,pdf
Classifier: Development Status :: 3 - Alpha
Classifier: Intended Audience :: Developers
Classifier: License :: OSI Approved :: MIT License
Classifier: Programming Language :: Python :: 3
Classifier: Programming Language :: Python :: 3.8
Classifier: Programming Language :: Python :: 3.9
Classifier: Programming Language :: Python :: 3.10
Classifier: Programming Language :: Python :: 3.11
Classifier: Programming Language :: Python :: 3.12
Classifier: Programming Language :: Python :: 3.13
Requires-Python: >=3.10
Requires-Dist: convert-markdown>=0.1.0
Requires-Dist: mcp[cli]>=1.17.0
